.DS_Store
disvoice_glottal/GCI.py
disvoice_glottal/__init__.py
disvoice_glottal/glottal.py
disvoice_glottal/peakdetect.py
disvoice_glottal/utils.py
disvoice_glottal/utils_gci.py
disvoice_glottal-0.0.5.dist-info/METADATA
disvoice_glottal-0.0.5.dist-info/WHEEL
disvoice_glottal-0.0.5.dist-info/top_level.txt
disvoice_glottal-0.0.5.dist-info/RECORD
